<?xml version="1.0" encoding="UTF-8"?>
<ROOT>
    <ELEMENTCFG>
        <CODIELEMEN>TBDATSISTE</CODIELEMEN>
        <CLSVERSION>sdai.com.sis.rednodal.datosdsistema.VersionadoDatosDSistema</CLSVERSION>
        <CLSCOMPARA>sdai.com.sis.rednodal.datosdsistema.ComparadorDatosDSistema</CLSCOMPARA>
    </ELEMENTCFG>
    <ELEMENTCFG>
        <CODIELEMEN>TBENTINODO</CODIELEMEN>
        <CLASELEMEN>sdai.com.sis.rednodal.nodos.XMLNodo</CLASELEMEN>
        <CLASADATOS>sdai.com.sis.rednodal.nodos.ADNodos</CLASADATOS>
        <METHODPERS>persistNodoVersion</METHODPERS>
    </ELEMENTCFG>
    <ELEMENTCFG>
        <CODIELEMEN>TBATRSNODO</CODIELEMEN>
        <CLASELEMEN>sdai.com.sis.rednodal.atributosdnodo.XMLAtributoDNodo</CLASELEMEN>
        <CLASADATOS>sdai.com.sis.rednodal.atributosdnodo.ADAtributosDNodo</CLASADATOS>
        <METHODPERS>persistAtributoDNodoVersion</METHODPERS>
    </ELEMENTCFG>
    <ELEMENTCFG>
        <CODIELEMEN>TBENTTUPLA</CODIELEMEN>
        <CLASELEMEN>sdai.com.sis.rednodal.tuplas.XMLTupla</CLASELEMEN>
        <CLASADATOS>sdai.com.sis.rednodal.tuplas.ADTuplas</CLASADATOS>
        <METHODPERS>persistTuplaVersion</METHODPERS>
    </ELEMENTCFG>
    <ELEMENTCFG>
        <CODIELEMEN>TBATRTUPLA</CODIELEMEN>
        <CLASELEMEN>sdai.com.sis.rednodal.atributosdtupla.XMLAtributoDTupla</CLASELEMEN>
        <CLASADATOS>sdai.com.sis.rednodal.atributosdtupla.ADAtributosDTupla</CLASADATOS>
        <METHODPERS>persistAtributoDTuplaVersion</METHODPERS>
    </ELEMENTCFG>
</ROOT>

